AUTHORS.rst
CONTRIBUTING.rst
HISTORY.rst
LICENSE
MANIFEST.in
README.rst
dvlpt_requirements.txt
requirements.txt
setup.cfg
setup.py
doc/Makefile
doc/authors.rst
doc/conf.py
doc/contributing.rst
doc/history.rst
doc/index.rst
doc/installation.rst
doc/make.bat
doc/readme.rst
doc/usage.rst
doc/user/autosum.rst
doc/user/index.rst
doc/user/manual.rst
src/openalea/__init__.py
src/openalea.deploy.egg-info/PKG-INFO
src/openalea.deploy.egg-info/SOURCES.txt
src/openalea.deploy.egg-info/dependency_links.txt
src/openalea.deploy.egg-info/entry_points.txt
src/openalea.deploy.egg-info/not-zip-safe
src/openalea.deploy.egg-info/top_level.txt
src/openalea/deploy/__init__.py
src/openalea/deploy/alea_config.py
src/openalea/deploy/alea_install.py
src/openalea/deploy/alea_update.py
src/openalea/deploy/autosum_generator.py
src/openalea/deploy/binary_deps.py
src/openalea/deploy/command.py
src/openalea/deploy/console.py
src/openalea/deploy/doc_tools.py
src/openalea/deploy/environ_var.py
src/openalea/deploy/gforge.py
src/openalea/deploy/gforge_util.py
src/openalea/deploy/install_lib.py
src/openalea/deploy/list_modules.py
src/openalea/deploy/metainfo.py
src/openalea/deploy/setup.py
src/openalea/deploy/shared_data.py
src/openalea/deploy/shortcut.py
src/openalea/deploy/util.py
src/openalea/deploy/version.py
src/openalea/deploy/system_dependencies/__init__.py
src/openalea/deploy/system_dependencies/dependency.py
src/openalea/deploy/system_dependencies/dependency_builder.py
src/openalea/deploy/system_dependencies/deploy_system.py
src/openalea/deploy/system_dependencies/deploy_system2.py
src/openalea/deploy/system_dependencies/distributions.py
src/openalea/deploy/system_dependencies/egg_rules.py
src/openalea/deploy/system_dependencies/patch.py
src/openalea/deploy/system_dependencies/project_rules.py
src/openalea/deploy/system_dependencies/qtpatch.py
src/openalea/deploy/system_dependencies/rpy2_setup.py
src/openalea/deploy/system_dependencies/ubuntu_release.py
test/__init__.py