Metadata-Version: 1.0
Name: openalea.deploy
Version: 2.0.0
Summary: OpenAlea.Deploy support the installation of OpenAlea packages via the network and manage their dependencies. It is an extension of Setuptools. 
Home-page: https://openalea.gforge.inria.fr
Author: openalea
Author-email: christophe dot pradal at cirad dot fr
License: cecill-c
Keywords: setuptools,openalea
Platform: UNKNOWN
